pfsc_core/__init__.py
pfsc_core-0.0.1.dist-info/LICENSE
pfsc_core-0.0.1.dist-info/METADATA
pfsc_core-0.0.1.dist-info/WHEEL
pfsc_core-0.0.1.dist-info/top_level.txt
pfsc_core-0.0.1.dist-info/RECORD
