Metadata-Version: 2.1
Name: pfsc-core
Version: 0.0.1
Summary: Proofscape Core
Author: Steve Kieffer
Author-email: sk@skieffer.info
License: Apache 2.0
Classifier: License :: OSI Approved :: Mozilla Public License 2.0 (MPL 2.0)
Classifier: Operating System :: OS Independent
Classifier: Programming Language :: Python :: 3
License-File: LICENSE
